{"groups":[{"type":"Nearby","venues":[{"id":152636,"name":"Cicero's","primarycategory":{"id":79081,"fullpathname":"Food:Pizza","nodename":"Pizza","iconurl":"http://foursquare.com/img/categories/food/pizza.png"},"address":"6691 Delmar Blvd","crossstreet":"at Kingsland Ave","city":"St. Louis","state":"MO","zip":"63130","verified":true,"geolat":38.6563397,"geolong":-90.3085238,"stats":{"herenow":"0"},"distance":336},{"id":152950,"name":"COCA (Center of Creative Arts)","primarycategory":{"id":78982,"fullpathname":"Arts & Entertainment:Performing Arts","nodename":"Performing Arts","iconurl":"http://foursquare.com/img/categories/arts_entertainment/default.png"},"address":"524 Trinity Avenue","crossstreet":"north of Delmar Avenue","city":"St. Louis","state":"MO","zip":"63130","verified":false,"geolat":38.65496,"geolong":-90.310782,"stats":{"herenow":"0"},"distance":105},{"id":6120944,"name":"The Delmar Loop","primarycategory":{"id":79169,"fullpathname":"Nightlife:Other - Nightlife","nodename":"Other - Nightlife","iconurl":"http://foursquare.com/img/categories/nightlife/default.png"},"address":"","city":"","state":"","verified":false,"geolat":38.65611111111111,"geolong":-90.30972222222222,"stats":{"herenow":"0"},"distance":233},{"id":7099743,"name":"Church Of Scientology","primarycategory":{"id":79142,"fullpathname":"Home / Work / Other:Religious:Church","nodename":"Church","iconurl":"http://foursquare.com/img/categories/building/religious_church.png"},"address":"6901 Delmar Blvd","city":"St Louis","state":"Missouri","zip":"63130","verified":false,"geolat":38.656653,"geolong":-90.311506,"stats":{"herenow":"0"},"distance":188},{"id":578722,"name":"560 Music Center","primarycategory":{"id":78983,"fullpathname":"Arts & Entertainment:Performing Arts:Concert Hall","nodename":"Concert Hall","iconurl":"http://foursquare.com/img/categories/arts_entertainment/default.png"},"address":"560 Trinity","crossstreet":"Delmar","city":"University City","state":"MO","zip":"63130","verified":false,"geolat":38.655647,"geolong":-90.31082,"stats":{"herenow":"0"},"distance":125},{"id":1954094,"name":"University City Public Library","primarycategory":{"id":79020,"fullpathname":"College & Education:Library","nodename":"Library","iconurl":"http://foursquare.com/img/categories/education/default.png"},"address":"6701 Delmar Boulevard","city":"University City","state":"MO","verified":false,"geolat":38.657131,"geolong":-90.309822,"stats":{"herenow":"0"},"distance":303},{"id":7210101,"name":"Fitz's","primarycategory":{"id":79039,"fullpathname":"Food:American","nodename":"American","iconurl":"http://foursquare.com/img/categories/food/default.png"},"address":"Delmar Loop","city":"University City","state":"Missouri","verified":false,"geolat":38.656519,"geolong":-90.310492,"stats":{"herenow":"0"},"distance":213},{"id":481967,"name":"US Post Office - University City","primarycategory":{"id":96354,"fullpathname":"Home / Work / Other:Post Office","nodename":"Post Office","iconurl":"http://foursquare.com/img/categories/building/postoffice.png"},"address":"561 Kingsland Ave","crossstreet":"Delmar","city":"St. Louis","state":"MO","zip":"63130","verified":false,"geolat":38.655968,"geolong":-90.309471,"stats":{"herenow":"0"},"phone":"3147261067","distance":244},{"id":7580948,"name":"Screenz","primarycategory":{"id":79252,"fullpathname":"Shops:Services:Internet Cafe","nodename":"Internet Cafe","iconurl":"http://foursquare.com/img/categories/shops/default.png"},"address":"Delmar","city":"St Louis","state":"Missouri","zip":"63130","verified":false,"geolat":38.656519,"geolong":-90.310492,"stats":{"herenow":"0"},"distance":213},{"id":9863262,"name":"Snarfs","primarycategory":{"id":79083,"fullpathname":"Food:Sandwiches","nodename":"Sandwiches","iconurl":"http://foursquare.com/img/categories/food/sandwiches.png"},"address":"","city":"","state":"","verified":false,"geolat":38.656909,"geolong":-90.310171,"stats":{"herenow":"0"},"distance":265},{"id":4535347,"name":"DeBaliviere Place Pool","primarycategory":{"id":79197,"fullpathname":"Parks & Outdoors:Pool","nodename":"Pool","iconurl":"http://foursquare.com/img/categories/parks_outdoors/pool.png"},"address":"Waterman","crossstreet":"Clara","city":"St Louis","state":"MO","verified":false,"geolat":38.652888,"geolong":-90.3117195,"stats":{"herenow":"0"},"distance":236},{"id":556606,"name":"Trinity Presbyterian Church","primarycategory":{"id":79142,"fullpathname":"Home / Work / Other:Religious:Church","nodename":"Church","iconurl":"http://foursquare.com/img/categories/building/religious_church.png"},"address":"6800 Washington Ave.","crossstreet":"Kingsland","city":"University City","state":"Missouri","zip":"63130","verified":false,"geolat":38.654758,"geolong":-90.3096039,"stats":{"herenow":"0"},"phone":"3147253840","distance":210},{"id":8448865,"name":"Bierman","address":"7001 waterman","crossstreet":"Big bend","city":"St Louis","state":"MO","verified":false,"geolat":38.653412,"geolong":-90.314826,"stats":{"herenow":"0"},"distance":302},{"id":3489687,"name":"550 Music Hall","address":"560 Trinity Avenue","crossstreet":"Delmar","city":"St Louis","state":"MO","verified":false,"geolat":38.655647,"geolong":-90.31082,"stats":{"herenow":"0"},"distance":125},{"id":5705190,"name":"Cheese-ology","address":"","city":"St. Louis","state":"MO","verified":false,"geolat":38.65611111111111,"geolong":-90.30972222222222,"stats":{"herenow":"0"},"distance":233},{"id":5540504,"name":"The Scientology Center","primarycategory":{"id":79215,"fullpathname":"Shops:Bank / Financial","nodename":"Bank / Financial","iconurl":"http://foursquare.com/img/categories/shops/financial.png"},"address":"","city":"St Louis","state":"MO","zip":"63130","verified":false,"geolat":38.656126,"geolong":-90.313958,"stats":{"herenow":"0"},"distance":211},{"id":6299812,"name":"The Emporium","primarycategory":{"id":79222,"fullpathname":"Shops:Drug Store / Pharmacy","nodename":"Drug Store / Pharmacy","iconurl":"http://foursquare.com/img/categories/shops/drugstore.png"},"address":"Delmar","crossstreet":"Limit","city":"St Louis","state":"MO","verified":false,"geolat":38.656519,"geolong":-90.310492,"stats":{"herenow":"0"},"distance":213},{"id":5070013,"name":"Brandt's","primarycategory":{"id":79049,"fullpathname":"Food:Café","nodename":"Café","iconurl":"http://foursquare.com/img/categories/food/cafe.png"},"address":"","city":"St Louis","state":"Missouri","zip":"63130","verified":false,"geolat":38.65611111111111,"geolong":-90.30972222222222,"stats":{"herenow":"0"},"distance":233},{"id":7873669,"name":"City of University City","primarycategory":{"id":79126,"fullpathname":"Home / Work / Other:Government:City Hall","nodename":"City Hall","iconurl":"http://foursquare.com/img/categories/building/default.png"},"address":"6801 Delmar Blvd","city":"University City","state":"MO","zip":"63130","verified":false,"geolat":38.6571638,"geolong":-90.3097844,"stats":{"herenow":"0"},"phone":"3145058544","distance":308},{"id":5745908,"name":"University City Hall","primarycategory":{"id":79126,"fullpathname":"Home / Work / Other:Government:City Hall","nodename":"City Hall","iconurl":"http://foursquare.com/img/categories/building/default.png"},"address":"6801 Delmar","city":"University City","state":"MO","verified":false,"geolat":38.6571638,"geolong":-90.3097844,"stats":{"herenow":"0"},"distance":308},{"id":9868520,"name":"6829 Kingsbury","address":"","city":"","state":"","verified":false,"geolat":38.654238,"geolong":-90.31071,"stats":{"herenow":"0"},"distance":140},{"id":6078969,"name":"Sigma Nu Apt 517","address":"517 Kingsland Ave","city":"Hadley","state":"Missouri","zip":"63130","verified":false,"geolat":38.6543629,"geolong":-90.309669,"stats":{"herenow":"0"},"distance":214},{"id":444033,"name":"E Desmond Lee Concert Hall","primarycategory":{"id":78968,"fullpathname":"Arts & Entertainment:Music Venue:Concert Hall","nodename":"Concert Hall","iconurl":"http://foursquare.com/img/categories/arts_entertainment/musicvenue.png"},"address":"560 Trinity Ave","city":"St. Louis","state":"MO","verified":false,"geolat":38.655647,"geolong":-90.31082,"stats":{"herenow":"0"},"distance":125},{"id":3983928,"name":"Center Of Creative Arts (COCA)","primarycategory":{"id":78984,"fullpathname":"Arts & Entertainment:Performing Arts:Dance Studio","nodename":"Dance Studio","iconurl":"http://foursquare.com/img/categories/arts_entertainment/default.png"},"address":"524 trinity ave","city":"University city","state":"MO","verified":false,"geolat":38.654864,"geolong":-90.310704,"stats":{"herenow":"0"},"distance":113},{"id":2709746,"name":"Prominent SEO","primarycategory":{"id":79115,"fullpathname":"Home / Work / Other:Corporate / Office","nodename":"Corporate / Office","iconurl":"http://foursquare.com/img/categories/building/default.png"},"address":"","city":"St Louis","state":"MO","zip":"63130","verified":false,"geolat":38.65397,"geolong":-90.31542,"stats":{"herenow":"0"},"distance":318},{"id":9121015,"name":"520 Kingsland","address":"","city":"","state":"","verified":false,"geolat":38.655021,"geolong":-90.309273,"stats":{"herenow":"0"},"distance":237},{"id":10584827,"name":"University United Methodist Church","primarycategory":{"id":79142,"fullpathname":"Home / Work / Other:Religious:Church","nodename":"Church","iconurl":"http://foursquare.com/img/categories/building/religious_church.png"},"address":"","city":"","state":"","verified":false,"geolat":38.655888,"geolong":-90.311615,"stats":{"herenow":"0"},"distance":104},{"id":10119836,"name":"Work","primarycategory":{"id":96353,"fullpathname":"Home / Work / Other:Event Space","nodename":"Event Space","iconurl":"http://foursquare.com/img/categories/building/default.png"},"address":"Delmar loop","city":"St Louis","state":"Missouri","zip":"63104","verified":false,"geolat":38.656519,"geolong":-90.310493,"stats":{"herenow":"0"},"distance":213},{"id":6515714,"name":"World's fair pavillion","primarycategory":{"id":79198,"fullpathname":"Parks & Outdoors:Scenic Lookout","nodename":"Scenic Lookout","iconurl":"http://foursquare.com/img/categories/parks_outdoors/default.png"},"address":"","crossstreet":"St louis","city":"St louis","state":"MO","verified":false,"geolat":38.65611111111111,"geolong":-90.30972222222222,"stats":{"herenow":"0"},"distance":233},{"id":12148614,"name":"Market Pub Households","address":"","city":"St Louis","state":"Missouri","zip":"63130","verified":false,"geolat":38.656057,"geolong":-90.309948,"stats":{"herenow":"0"},"distance":213},{"id":7651613,"name":"Danny Davies'","address":"","city":"","state":"","verified":false,"geolat":38.654849,"geolong":-90.309182,"stats":{"herenow":"0"},"distance":245},{"id":6508116,"name":"Alterboush","address":"Delmar","crossstreet":"Westgate","city":"St. Louis","state":"Mo","verified":false,"geolat":38.656519,"geolong":-90.310492,"stats":{"herenow":"0"},"distance":213},{"id":3491615,"name":"Grace Umc","primarycategory":{"id":79142,"fullpathname":"Home / Work / Other:Religious:Church","nodename":"Church","iconurl":"http://foursquare.com/img/categories/building/religious_church.png"},"address":"Waterman","crossstreet":"Skinker","city":"St Louis","state":"MO","verified":false,"geolat":38.652888,"geolong":-90.3117195,"stats":{"herenow":"0"},"distance":236},{"id":379080,"name":"University City Public Library","address":"6701 Delmar Boulevard","crossstreet":"Kingsland","city":"St. Louis","state":"MO","zip":"63130","verified":false,"geolat":38.657131,"geolong":-90.309822,"stats":{"herenow":"0"},"phone":"3147273150","distance":303},{"id":11467403,"name":"Melting Pot","address":"","city":"St Louis","state":"Missouri","zip":"63130","verified":false,"geolat":38.656089,"geolong":-90.313055,"stats":{"herenow":"0"},"distance":152},{"id":11269661,"name":"Bais Abe Congregation","primarycategory":{"id":79141,"fullpathname":"Home / Work / Other:Religious","nodename":"Religious","iconurl":"http://foursquare.com/img/categories/building/religious.png"},"address":"","city":"","state":"","verified":false,"geolat":38.65611761,"geolong":-90.31200693,"stats":{"herenow":"0"},"distance":124},{"id":3794446,"name":"#1 Bus Shelter","primarycategory":{"id":96362,"fullpathname":"Travel:Bus Station:Bus","nodename":"Bus","iconurl":"http://foursquare.com/img/categories/travel/busstation.png"},"address":"Waterman","crossstreet":"Skinker","city":"St Louis","state":"MO","verified":false,"geolat":38.652888,"geolong":-90.3117195,"stats":{"herenow":"0"},"distance":236},{"id":3645695,"name":"1 Goldline","primarycategory":{"id":79268,"fullpathname":"Travel:Bus Station","nodename":"Bus Station","iconurl":"http://foursquare.com/img/categories/travel/busstation.png"},"address":"Waterman","crossstreet":"Skinker","city":"St Louis","state":"MO","verified":false,"geolat":38.652888,"geolong":-90.3117195,"stats":{"herenow":"0"},"distance":236},{"id":10150806,"name":"My house","address":"Tulane","city":"","state":"","verified":false,"geolat":38.657434,"geolong":-90.312984,"stats":{"herenow":"0"},"distance":284},{"id":9734758,"name":"Circle K","address":"Delmar","crossstreet":"Skinker","city":"St. Louis","state":"MO","verified":false,"geolat":38.656519,"geolong":-90.310493,"stats":{"herenow":"0"},"distance":213},{"id":3687879,"name":"Next Dor","primarycategory":{"id":79144,"fullpathname":"Home / Work / Other:Religious:Synagogue","nodename":"Synagogue","iconurl":"http://foursquare.com/img/categories/building/religious_synagogue.png"},"address":"Waterman","crossstreet":"Kingshighway","city":"St Louis","state":"MO","verified":false,"geolat":38.652888,"geolong":-90.3117195,"stats":{"herenow":"0"},"distance":236},{"id":4247873,"name":"My Cave","address":"6833 Waterman Ave","city":"St Louis","state":"MO","verified":false,"geolat":38.65313,"geolong":-90.31108,"stats":{"herenow":"0"},"distance":223},{"id":11467226,"name":"The Melting 0ot","address":"","city":"St Louis","state":"Missouri","zip":"63130","verified":false,"geolat":38.656089,"geolong":-90.313055,"stats":{"herenow":"0"},"distance":152},{"id":10784328,"name":"Kappa Kappa Gamma Suite","address":"","city":"","state":"","verified":false,"geolat":38.656066,"geolong":-90.309143,"stats":{"herenow":"0"},"distance":275},{"id":3205423,"name":"Clark Schultz's office","address":"","city":"St Louis","state":"MO","zip":"63130","verified":false,"geolat":38.65404,"geolong":-90.31552,"stats":{"herenow":"0"},"distance":324},{"id":11979378,"name":"University City Police","primarycategory":{"id":79131,"fullpathname":"Home / Work / Other:Government:Police Station","nodename":"Police Station","iconurl":"http://foursquare.com/img/categories/building/default.png"},"address":"6801 Delmar","city":"University City","state":"MO","zip":"63130","verified":false,"geolat":38.6571638,"geolong":-90.3097844,"stats":{"herenow":"0"},"distance":308},{"id":10722771,"name":"Quadrangle Housing","address":"6820 Delmar Blvd","crossstreet":"at Sgt. Mike King Dr","city":"Saint Louis","state":"MO","zip":"63130","verified":true,"geolat":38.656078,"geolong":-90.309895,"stats":{"herenow":"0"},"phone":"3149359511","distance":218},{"id":5600950,"name":"Danny's Place","address":"","city":"St Louis","state":"Missouri","zip":"63130","verified":false,"geolat":38.656334,"geolong":-90.31404,"stats":{"herenow":"0"},"distance":231},{"id":152730,"name":"Sista Speak","primarycategory":{"id":79130,"fullpathname":"Home / Work / Other:Government:Monument / Landmark","nodename":"Monument / Landmark","iconurl":"http://foursquare.com/img/categories/building/default.png"},"address":"6691 Delmar Boulevard","city":"St. Louis","state":"MO","zip":"63130","verified":false,"geolat":38.656418,"geolong":-90.30898,"stats":{"herenow":"0"},"distance":306},{"id":10728432,"name":"Quadrangle Housing","address":"6677 Washington Ave","city":"St.Louis","state":"MO","zip":"63130","verified":false,"geolat":38.655337,"geolong":-90.308869,"stats":{"herenow":"0"},"phone":"3149359511","twitter":"QuadrangleSTL","distance":274}]}]}